[{"step":1,"name":"median income by location","chart":"bar","bartype":"bar","format":"dollar","color":"colorByLoc","projection":"vertical","left":40,"moves":1,"hasLegend":0},{"step":2,"name":"poverty by location","chart":"bar","bartype":"bar","format":"percent","color":"colorByLoc","projection":"vertical","left":40,"moves":1,"hasLegend":0},{"step":3,"name":"median income by race & sex","chart":"bar","bartype":"clusterbar","format":"dollar","color":"colorBySex","projection":"vertical","left":40,"moves":1,"hasLegend":1},{"step":4,"name":"poverty by race & sex","chart":"bar","bartype":"clusterbar","format":"percent","color":"colorBySex","projection":"vertical","left":40,"moves":1,"hasLegend":1},{"step":5,"name":"unemployment statewide","chart":"time","format":"percent","color":"colorByLoc","left":40,"moves":1,"hasLegend":0},{"step":6,"name":"unemployment by race","chart":"time","format":"percent","color":"colorByRace","left":40,"moves":1,"hasLegend":1},{"step":7,"name":"financially insecure by race & sex","chart":"bar","bartype":"clusterbar","format":"percent","color":"colorBySex","projection":"vertical","left":40,"moves":1,"hasLegend":1},{"step":8,"name":"security index by race","chart":"bar","bartype":"clusterbar","format":"percent","color":"colorByRace","projection":"horizontal","left":130,"moves":1,"hasLegend":1},{"step":9,"name":"homeownership by race","chart":"bar","bartype":"bar","format":"percent","color":"colorByLoc","projection":"vertical","left":40,"moves":1,"hasLegend":0},{"step":10,"name":"homeownership by race & type","chart":"bar","bartype":"clusterbar","format":"percent","color":"colorByHome","projection":"vertical","left":40,"moves":1,"hasLegend":1},{"step":11,"name":"homeownership by age","chart":"bar","bartype":"bar","format":"percent","color":"colorByLoc","projection":"vertical","left":40,"moves":1,"hasLegend":0},{"step":12,"name":"homeownership by race & age","chart":"bar","bartype":"clusterbar","format":"percent","color":"colorByAge","projection":"vertical","left":40,"moves":1,"hasLegend":1},{"step":13,"name":"burden by race & type","chart":"bar","bartype":"clusterbar","format":"percent","color":"colorByHome","projection":"vertical","left":40,"moves":1,"hasLegend":1},{"step":14,"name":"financially secure by race & sex","chart":"bar","bartype":"clusterbar","format":"percent","color":"colorBySex","projection":"vertical","left":40,"moves":2,"hasLegend":1}]
